currency_symbols/__init__.py
currency_symbols/_constants.py
currency_symbols/currency_symbols.py
currency_symbols/test.py
currency_symbols-2.0.4.dist-info/licenses/LICENSE
currency_symbols-2.0.4.dist-info/METADATA
currency_symbols-2.0.4.dist-info/WHEEL
currency_symbols-2.0.4.dist-info/top_level.txt
currency_symbols-2.0.4.dist-info/RECORD
