Metadata-Version: 2.4
Name: currency-symbols
Version: 2.0.4
Summary: Get currency symbol by currency code
Home-page: https://github.com/arshadkazmi42/currency-symbols
Author: Arshad Kazmi
Author-email: arshadkazmi42@gmail.com
Classifier: Programming Language :: Python :: 3
Classifier: License :: OSI Approved :: MIT License
Classifier: Operating System :: OS Independent
License-File: LICENSE
Dynamic: author
Dynamic: author-email
Dynamic: classifier
Dynamic: description
Dynamic: description-content-type
Dynamic: home-page
Dynamic: license-file
Dynamic: summary
